__init__.py
lingua_characteristica/__init__.py
lingua_characteristica-0.0.2.dist-info/LICENSE
lingua_characteristica-0.0.2.dist-info/METADATA
lingua_characteristica-0.0.2.dist-info/WHEEL
lingua_characteristica-0.0.2.dist-info/top_level.txt
lingua_characteristica-0.0.2.dist-info/RECORD
