Metadata-Version: 2.1
Name: lingua-characteristica
Version: 0.0.2
Summary: Lingua Characteristica Universalis
Author-email: Alexander Fedotov <alex.fedotov@aol.com>
Project-URL: Homepage, https://github.com/lingua-characteristica/lingua-characteristica
Project-URL: Bug Tracker, https://github.com/lingua-characteristica/lingua-characteristica/issues
Classifier: Programming Language :: Python :: 3
Classifier: License :: OSI Approved :: MIT License
Classifier: Operating System :: OS Independent
Requires-Python: >=3.10
License-File: LICENSE
